celery_hchecker/__init__.py
celery_hchecker/cache/__init__.py
celery_hchecker/cache/base.py
celery_hchecker/cache/memory.py
celery_hchecker/cache/redis.py
celery_hchecker/checkers/__init__.py
celery_hchecker/checkers/backend.py
celery_hchecker/checkers/base.py
celery_hchecker/checkers/broker.py
celery_hchecker/checkers/workers.py
celery_hchecker/healthchecker.py
celery_hchecker-0.0.3.dist-info/METADATA
celery_hchecker-0.0.3.dist-info/WHEEL
celery_hchecker-0.0.3.dist-info/RECORD
