Metadata-Version: 2.4
Name: celery-hchecker
Version: 0.0.3
Summary: 
Author: skulap
Author-email: skulap01@gmail.com
Requires-Python: >=3.12
Classifier: Programming Language :: Python :: 3
Classifier: Programming Language :: Python :: 3.12
Classifier: Programming Language :: Python :: 3.13
Classifier: Programming Language :: Python :: 3.14
Requires-Dist: cachetools (>=6.2.0,<7.0.0)
Requires-Dist: celery (>=5.5.3,<6.0.0)
